[
  {
    "num": 1,
    "timestamp": "2026-03-22T11:56:18.200970+00:00",
    "status": "crash",
    "cold_launch_ms": 0,
    "composite_score": 0.0,
    "description": "Delay non-critical services and analytics initialization until after first render to improve perceived launch performance.",
    "input_tokens": 5209,
    "output_tokens": 1891,
    "cost_usd": 0.002498,
    "api_seconds": 44.9,
    "files_changed": 2,
    "lines_changed": 209,
    "build_seconds": 0
  },
  {
    "num": 2,
    "timestamp": "2026-03-22T13:59:40.373385+00:00",
    "status": "discard",
    "cold_launch_ms": 590,
    "composite_score": 0.9279,
    "description": "Move heavy view model initialization in MainView to background tasks and only initialize the currently selected tab's view model first.",
    "input_tokens": 5741,
    "output_tokens": 2381,
    "cost_usd": 0.002982,
    "api_seconds": 86.7,
    "files_changed": 1,
    "lines_changed": 211,
    "build_seconds": 15.7
  },
  {
    "num": 3,
    "timestamp": "2026-03-22T14:03:29.764696+00:00",
    "status": "discard",
    "cold_launch_ms": 629,
    "composite_score": 0.8187,
    "description": "Move ModelContainer creation to background thread and delay non-essential view model initialization until after first render.",
    "input_tokens": 5776,
    "output_tokens": 2403,
    "cost_usd": 0.003006,
    "api_seconds": 195.8,
    "files_changed": 2,
    "lines_changed": 97,
    "build_seconds": 15.9
  },
  {
    "num": 4,
    "timestamp": "2026-03-22T14:04:23.837045+00:00",
    "status": "crash",
    "cold_launch_ms": 0,
    "composite_score": 0.0,
    "description": "Here's my hypothesis for improving cold launch time:",
    "input_tokens": 5809,
    "output_tokens": 1918,
    "cost_usd": 0.002639,
    "api_seconds": 48.4,
    "files_changed": 2,
    "lines_changed": 208,
    "build_seconds": 0
  },
  {
    "num": 5,
    "timestamp": "2026-03-22T14:09:56.590428+00:00",
    "status": "keep",
    "cold_launch_ms": 462,
    "composite_score": 1.1896,
    "description": "Delay non-essential view model initialization in MainView until after first render and move heavy operations to background.",
    "input_tokens": 5830,
    "output_tokens": 3626,
    "cost_usd": 0.003958,
    "api_seconds": 310.2,
    "files_changed": 2,
    "lines_changed": 276,
    "build_seconds": 8.8
  },
  {
    "num": 6,
    "timestamp": "2026-03-22T14:12:58.222056+00:00",
    "status": "keep",
    "cold_launch_ms": 389,
    "composite_score": 1.3756,
    "description": "Further optimize cold launch by moving ModelContainer creation to background thread and delaying analytics services initialization until after first render.",
    "input_tokens": 6571,
    "output_tokens": 2383,
    "cost_usd": 0.003149,
    "api_seconds": 162.6,
    "files_changed": 2,
    "lines_changed": 121,
    "build_seconds": 5.6
  },
  {
    "num": 7,
    "timestamp": "2026-03-22T14:14:46.396715+00:00",
    "status": "keep",
    "cold_launch_ms": 356,
    "composite_score": 1.4758,
    "description": "Further optimize cold launch by reducing splash screen duration and moving more service initialization to background threads.",
    "input_tokens": 6619,
    "output_tokens": 2466,
    "cost_usd": 0.003223,
    "api_seconds": 89.0,
    "files_changed": 2,
    "lines_changed": 165,
    "build_seconds": 5.9
  },
  {
    "num": 8,
    "timestamp": "2026-03-22T14:15:25.997922+00:00",
    "status": "discard",
    "cold_launch_ms": 356,
    "composite_score": 1.4415,
    "description": "Further optimize cold launch by reducing splash screen animation duration and moving more initialization work to background threads.",
    "input_tokens": 6705,
    "output_tokens": 849,
    "cost_usd": 0.001995,
    "api_seconds": 20.5,
    "files_changed": 1,
    "lines_changed": 1,
    "build_seconds": 5.8
  },
  {
    "num": 9,
    "timestamp": "2026-03-22T14:17:22.420891+00:00",
    "status": "keep",
    "cold_launch_ms": 351,
    "composite_score": 1.525,
    "description": "Further optimize cold launch by moving more service initialization to background threads and reducing splash screen animation duration.",
    "input_tokens": 6736,
    "output_tokens": 1319,
    "cost_usd": 0.002363,
    "api_seconds": 96.3,
    "files_changed": 2,
    "lines_changed": 3,
    "build_seconds": 6.7
  },
  {
    "num": 10,
    "timestamp": "2026-03-22T14:23:53.489677+00:00",
    "status": "crash",
    "cold_launch_ms": 0,
    "composite_score": 0.0,
    "description": "Further optimize cold launch by delaying more view model initialization in MainView and moving additional service work to background threads.",
    "input_tokens": 6772,
    "output_tokens": 3683,
    "cost_usd": 0.00419,
    "api_seconds": 357.1,
    "files_changed": 2,
    "lines_changed": 259,
    "build_seconds": 0
  },
  {
    "num": 11,
    "timestamp": "2026-03-22T14:27:05.123175+00:00",
    "status": "keep",
    "cold_launch_ms": 344,
    "composite_score": 1.4666,
    "description": "Further optimize cold launch by delaying more view model initialization and moving remaining heavy operations to background threads after first render.",
    "input_tokens": 6806,
    "output_tokens": 2248,
    "cost_usd": 0.003092,
    "api_seconds": 170.1,
    "files_changed": 1,
    "lines_changed": 212,
    "build_seconds": 8.0
  },
  {
    "num": 12,
    "timestamp": "2026-03-22T14:51:36.048014+00:00",
    "status": "crash",
    "cold_launch_ms": 0,
    "composite_score": 0.0,
    "description": "Further optimize cold launch by reducing splash screen animation duration and moving SpotlightService indexing to background.",
    "input_tokens": 6023,
    "output_tokens": 1224,
    "cost_usd": 0.002147,
    "api_seconds": 25.7,
    "files_changed": 2,
    "lines_changed": 32,
    "build_seconds": 0
  },
  {
    "num": 13,
    "timestamp": "2026-03-22T14:53:11.127574+00:00",
    "status": "crash",
    "cold_launch_ms": 0,
    "composite_score": 0.0,
    "description": "I'll optimize the cold launch time by focusing on deferring and parallelizing non-essential initiali",
    "input_tokens": 6019,
    "output_tokens": 2365,
    "cost_usd": 0.003025,
    "api_seconds": 55.5,
    "files_changed": 2,
    "lines_changed": 209,
    "build_seconds": 0
  },
  {
    "num": 14,
    "timestamp": "2026-03-22T14:54:03.365104+00:00",
    "status": "crash",
    "cold_launch_ms": 0,
    "composite_score": 0.0,
    "description": "Further optimize cold launch by moving ModelContainer creation to background thread before the first render.",
    "input_tokens": 6019,
    "output_tokens": 1284,
    "cost_usd": 0.002192,
    "api_seconds": 47.9,
    "files_changed": 1,
    "lines_changed": 66,
    "build_seconds": 0
  },
  {
    "num": 15,
    "timestamp": "2026-03-22T14:55:22.500144+00:00",
    "status": "crash",
    "cold_launch_ms": 0,
    "composite_score": 0.0,
    "description": "Further optimize cold launch by moving ModelContainer creation to background thread before first render and reducing splash screen duration.",
    "input_tokens": 6026,
    "output_tokens": 1269,
    "cost_usd": 0.002182,
    "api_seconds": 73.6,
    "files_changed": 2,
    "lines_changed": 66,
    "build_seconds": 0
  },
  {
    "num": 16,
    "timestamp": "2026-03-22T15:00:04.414568+00:00",
    "status": "keep",
    "cold_launch_ms": 405,
    "composite_score": 1.2049,
    "description": "Reduce cold launch time by moving ModelContainer creation to a background thread during app initialization and delaying non-essential view model creation until after first render.",
    "input_tokens": 6028,
    "output_tokens": 2819,
    "cost_usd": 0.003376,
    "api_seconds": 257.4,
    "files_changed": 2,
    "lines_changed": 18,
    "build_seconds": 9.8
  },
  {
    "num": 17,
    "timestamp": "2026-03-22T15:01:08.409527+00:00",
    "status": "crash",
    "cold_launch_ms": 0,
    "composite_score": 0.0,
    "description": "After analyzing the code, here's my hypothesis for optimizing cold launch time:",
    "input_tokens": 6029,
    "output_tokens": 2210,
    "cost_usd": 0.002907,
    "api_seconds": 59.3,
    "files_changed": 3,
    "lines_changed": 194,
    "build_seconds": 0
  },
  {
    "num": 18,
    "timestamp": "2026-03-22T15:02:51.437877+00:00",
    "status": "discard",
    "cold_launch_ms": 457,
    "composite_score": 1.0968,
    "description": "Further optimize cold launch by reducing splash screen animation duration and moving more view model initialization to after first render.",
    "input_tokens": 6026,
    "output_tokens": 2673,
    "cost_usd": 0.003263,
    "api_seconds": 78.7,
    "files_changed": 2,
    "lines_changed": 139,
    "build_seconds": 9.5
  },
  {
    "num": 19,
    "timestamp": "2026-03-22T15:05:23.244212+00:00",
    "status": "discard",
    "cold_launch_ms": 587,
    "composite_score": 0.8609,
    "description": "Further optimize cold launch by reducing splash screen animation duration and moving more view model initialization to after first render.",
    "input_tokens": 6028,
    "output_tokens": 2615,
    "cost_usd": 0.003219,
    "api_seconds": 117.3,
    "files_changed": 2,
    "lines_changed": 73,
    "build_seconds": 16.8
  },
  {
    "num": 20,
    "timestamp": "2026-03-22T15:06:10.914649+00:00",
    "status": "crash",
    "cold_launch_ms": 0,
    "composite_score": 0.0,
    "description": "Further optimize cold launch by reducing splash screen animation duration and moving more service initialization to background threads.",
    "input_tokens": 6032,
    "output_tokens": 1932,
    "cost_usd": 0.002694,
    "api_seconds": 42.2,
    "files_changed": 2,
    "lines_changed": 144,
    "build_seconds": 0
  },
  {
    "num": 21,
    "timestamp": "2026-03-22T15:08:34.783756+00:00",
    "status": "discard",
    "cold_launch_ms": 541,
    "composite_score": 0.9158,
    "description": "Further optimize cold launch by moving AnalyticsService initialization to background and reducing splash screen animation duration.",
    "input_tokens": 6028,
    "output_tokens": 2186,
    "cost_usd": 0.002889,
    "api_seconds": 113.8,
    "files_changed": 2,
    "lines_changed": 95,
    "build_seconds": 14.1
  }
]